{
    "filters" : [
        {
            "column_name": "ACTUAL_INSP_DATE",
            "column_data_type": "date",
            "condition": [
                {
                    "and": {
                        "greater": "2019-06-30"
                    }
                }
            ]   
        },
        {
            "column_name": "COMPANY_NAME",
            "column_data_type": "string",
            "condition": [
                {
                    "and": {
                        "contains": "footwear"
                    }
                }
            ]   
        }
    ]
}